index.html
dystic/__init__.py
dystic/builder.py
dystic/config.py
dystic/configurator.py
dystic/database.py
dystic/indexer.py
dystic/main.py
dystic/marker.py
dystic/templater.py
dystic/utils.py
dystic-0.3.2.dist-info/DESCRIPTION.rst
dystic-0.3.2.dist-info/METADATA
dystic-0.3.2.dist-info/RECORD
dystic-0.3.2.dist-info/WHEEL
dystic-0.3.2.dist-info/entry_points.txt
dystic-0.3.2.dist-info/metadata.json
dystic-0.3.2.dist-info/top_level.txt
