Metadata-Version: 2.0
Name: dystic
Version: 0.3.2
Summary: a static site generator using dynamic principles
Home-page: https://github.com/MiteshNinja/dystic
Author: Mitesh Shah
Author-email: mitesh@miteshshah.com
License: UNKNOWN
Download-URL: https://github.com/MiteshNinja/dystic/tarball/0.3.2
Keywords: blog,generator,static,dynamic,dystic
Platform: UNKNOWN
Requires-Dist: jinja2
Requires-Dist: mistune
Requires-Dist: pygments
Requires-Dist: pyyaml
